[
	{ "code": "CGK", "city": "Jakarta" },
	{ "code": "SUB", "city": "Surabaya" },
	{ "code": "DPS", "city": "Denpasar" },
	{ "code": "UPG", "city": "Makassar" },
	{ "code": "BPN", "city": "Balikpapan" },
	{ "code": "JOG", "city": "Yogyakarta" },
	{ "code": "SRG", "city": "Semarang" },
	{ "code": "BTH", "city": "Batam" },
	{ "code": "PKU", "city": "Pekanbaru" },
	{ "code": "ARD", "city": "Alor Island" },
	{ "code": "AMQ", "city": "Ambon" },
	{ "code": "ABU", "city": "Atambua" },
	{ "code": "BTJ", "city": "Banda Aceh" },
	{ "code": "TKG", "city": "Bandar Lampung" },
	{ "code": "BDO", "city": "Bandung" },
	{ "code": "BDJ", "city": "Banjarmasin" },
	{ "code": "BWX", "city": "Banyuwangi" },
	{ "code": "BUW", "city": "Baubau" },
	{ "code": "BKS", "city": "Bengkulu" },
	{ "code": "BEJ", "city": "Berau" },
	{ "code": "BIK", "city": "Biak" },
	{ "code": "BMU", "city": "Bima" },
	{ "code": "WUB", "city": "Buli" },
	{ "code": "ENE", "city": "Ende" },
	{ "code": "FKQ", "city": "Fak Fak" },
	{ "code": "GTO", "city": "Gorontalo" },
	{ "code": "GNS", "city": "Gunung Sitoli" },
	{ "code": "HLP", "city": "Jakarta Halim" },
	{ "code": "DJB", "city": "Jambi" },
	{ "code": "DJJ", "city": "Jayapura" },
	{ "code": "KBU", "city": "Kotabaru" },
	{ "code": "KNG", "city": "Kaimana" },
	{ "code": "KDI", "city": "Kendari" },
	{ "code": "KTG", "city": "Ketapang" },
	{ "code": "KOE", "city": "Kupang" },
	{ "code": "LBJ", "city": "Labuanbajo" },
	{ "code": "LAH", "city": "Labuha" },
	{ "code": "LKA", "city": "Larantuka" },
	{ "code": "LSW", "city": "Lhokseumawe" },
	{ "code": "LOP", "city": "Lombok" },
	{ "code": "LUW", "city": "Luwuk" },
	{ "code": "MLG", "city": "Malang" },
	{ "code": "MJU", "city": "Mamuju" },
	{ "code": "MDC", "city": "Manado" },
	{ "code": "MKW", "city": "Manokwari" },
	{ "code": "MOF", "city": "Maumere" },
	{ "code": "KNO", "city": "Medan" },
	{ "code": "MNA", "city": "Melonguane" },
	{ "code": "MKQ", "city": "Merauke" },
	{ "code": "MEQ", "city": "Meulaboh" },
	{ "code": "NBX", "city": "Nabire" },
	{ "code": "NTX", "city": "Natuna" },
	{ "code": "NNX", "city": "Nunukan" },
	{ "code": "PDG", "city": "Padang" },
	{ "code": "PKY", "city": "Palangkaraya" },
	{ "code": "PLM", "city": "Palembang" },
	{ "code": "PLW", "city": "Palu" },
	{ "code": "NSW", "city": "Pangandaran" },
	{ "code": "PGK", "city": "Pangkal Pinang" },
	{ "code": "PKN", "city": "Pangkalan Bun" },
	{ "code": "PUM", "city": "Pomala" },
	{ "code": "PNK", "city": "Pontianak" },
	{ "code": "PSJ", "city": "Poso" },
	{ "code": "RTG", "city": "Ruteng" },
	{ "code": "SRI", "city": "Samarinda" },
	{ "code": "SMQ", "city": "Sampit" },
	{ "code": "FLZ", "city": "Sibolga" },
	{ "code": "DTB", "city": "Silangit" },
	{ "code": "SOC", "city": "Solo" }
]
